majordomo_ai/__init__.py
majordomo_ai/auth.py
majordomo_ai/data_store.py
majordomo_ai/ingest_pipeline.py
majordomo_ai/models.py
majordomo_ai/query_pipeline.py
majordomo_ai-0.1.18.dist-info/METADATA
majordomo_ai-0.1.18.dist-info/WHEEL
majordomo_ai-0.1.18.dist-info/top_level.txt
majordomo_ai-0.1.18.dist-info/RECORD
